examples/__init__.py
examples/basic.py
examples/expression-problem.py
protoclass/__init__.py
protoclass/proto.py
protoclass-0.5.5.dist-info/LICENSE
protoclass-0.5.5.dist-info/METADATA
protoclass-0.5.5.dist-info/WHEEL
protoclass-0.5.5.dist-info/top_level.txt
protoclass-0.5.5.dist-info/zip-safe
protoclass-0.5.5.dist-info/RECORD
